py_process_hooker/__init__.py
py_process_hooker/hook32.py
py_process_hooker/hook64.py
py_process_hooker/inject_dll.py
py_process_hooker/winapi.py
py_process_hooker/dll/AnyHook.dll
py_process_hooker/dll/DetourHook.dll
py_process_hooker/dll/injectpy32.dll
py_process_hooker/dll/injectpy64.dll
py_process_hooker-0.3.0.dist-info/METADATA
py_process_hooker-0.3.0.dist-info/WHEEL
py_process_hooker-0.3.0.dist-info/licenses/LICENSE
py_process_hooker-0.3.0.dist-info/RECORD
