Metadata-Version: 2.3
Name: py-process-hooker
Version: 0.3.0
Summary: Inject python into other processes and implement Hook and active calls, supporting x86 and x64
Project-URL: Homepage, https://github.com/kanadeblisst00/py_hooker
Project-URL: Bug Tracker, https://github.com/kanadeblisst00/py_hooker/issues
Author-email: kanadeblisst <kanade@blisst.cn>
License: Copyright (c) 2018 The Python Packaging Authority
License-File: LICENSE
Classifier: License :: OSI Approved :: MIT License
Classifier: Programming Language :: Python :: 3
Requires-Python: >=3.7
Requires-Dist: module-hot-loading
Requires-Dist: psutil
